MANIFEST.in
README.md
setup.cfg
setup.py
mastertables/__init__.py
mastertables/cache.py
mastertables/help.py
mastertables/mastertables.py
mastertables.egg-info/PKG-INFO
mastertables.egg-info/SOURCES.txt
mastertables.egg-info/dependency_links.txt
mastertables.egg-info/entry_points.txt
mastertables.egg-info/requires.txt
mastertables.egg-info/top_level.txt