Metadata-Version: 2.1
Name: mastertables
Version: 1.0.0
Summary: A Python package to interact with the mastertables.athento.com public API
Home-page: https://github.com/athento/mastertables
Author: Athento
Author-email: adm@athento.com
License: UNKNOWN
Project-URL: Bug Reports, https://github.com/athento/mastertables/issues
Project-URL: Athento, https://athento.com
Project-URL: Mastertables, https://mastertables.athento.com
Keywords: api rest mastertables development data athento
Platform: UNKNOWN
Classifier: Development Status :: 5 - Production/Stable
Classifier: Intended Audience :: Developers
Classifier: Intended Audience :: End Users/Desktop
Classifier: Intended Audience :: Information Technology
Classifier: Intended Audience :: Science/Research
Classifier: Intended Audience :: System Administrators
Classifier: Intended Audience :: Telecommunications Industry
Classifier: Operating System :: OS Independent
Classifier: Topic :: Database :: Database Engines/Servers
Classifier: Topic :: Internet :: WWW/HTTP :: Dynamic Content
Classifier: Topic :: Software Development :: Libraries :: Python Modules
Classifier: License :: OSI Approved :: Apache Software License
Classifier: Programming Language :: Python
Classifier: Programming Language :: Python :: 2
Classifier: Programming Language :: Python :: 3
